meta_package_manager/__init__.py
meta_package_manager/__main__.py
meta_package_manager/bar_plugin.py
meta_package_manager/base.py
meta_package_manager/capabilities.py
meta_package_manager/cli.py
meta_package_manager/inventory.py
meta_package_manager/labels.py
meta_package_manager/managers/__init__.py
meta_package_manager/managers/apm.py
meta_package_manager/managers/apt.py
meta_package_manager/managers/cargo.py
meta_package_manager/managers/chocolatey.py
meta_package_manager/managers/composer.py
meta_package_manager/managers/dnf.py
meta_package_manager/managers/emerge.py
meta_package_manager/managers/eopkg.py
meta_package_manager/managers/flatpak.py
meta_package_manager/managers/fwupd.py
meta_package_manager/managers/gem.py
meta_package_manager/managers/homebrew.py
meta_package_manager/managers/mas.py
meta_package_manager/managers/npm.py
meta_package_manager/managers/opkg.py
meta_package_manager/managers/pacman.py
meta_package_manager/managers/pip.py
meta_package_manager/managers/pipx.py
meta_package_manager/managers/pkg.py
meta_package_manager/managers/scoop.py
meta_package_manager/managers/snap.py
meta_package_manager/managers/steamcmd.py
meta_package_manager/managers/uv.py
meta_package_manager/managers/vscode.py
meta_package_manager/managers/winget.py
meta_package_manager/managers/yarn.py
meta_package_manager/managers/zypper.py
meta_package_manager/output.py
meta_package_manager/pool.py
meta_package_manager/py.typed
meta_package_manager/sbom.py
meta_package_manager/specifier.py
meta_package_manager/version.py
meta_package_manager-6.1.0.dist-info/licenses/license
meta_package_manager-6.1.0.dist-info/WHEEL
meta_package_manager-6.1.0.dist-info/entry_points.txt
meta_package_manager-6.1.0.dist-info/METADATA
meta_package_manager-6.1.0.dist-info/RECORD
