Metadata-Version: 2.4
Name: meta-package-manager
Version: 6.1.0
Summary: 🎁 wraps all package managers with a unifying CLI
Keywords: CLI,apm,apt,apt-mint,atom,brew,cargo,cask,choco,chocotaley,composer,cyclonedx,dnf,dnf5,emerge,eopkg,flatpak,fwupd,gem,homebrew,mac app store,macos,mas,node,npm,opkg,package,package url,pacaur,pacman,paru,php composer,pip,pipx,pkg,plugin,portage,purl,ruby,rust,sbom,scoop,snap,spdx,steamcmd,uv,uvx,visual studio code,vscode,vscodium,xbar,swiftbar,winget,yarn,yay,yum,zypper
Author: Kevin Deldycke
Author-email: Kevin Deldycke <kevin@deldycke.com>
License-File: license
Classifier: Development Status :: 5 - Production/Stable
Classifier: Environment :: Console
Classifier: Environment :: MacOS X
Classifier: Environment :: Plugins
Classifier: Intended Audience :: Developers
Classifier: Intended Audience :: Information Technology
Classifier: Intended Audience :: System Administrators
Classifier: License :: OSI Approved :: GNU General Public License v2 or later (GPLv2+)
Classifier: Operating System :: MacOS :: MacOS X
Classifier: Operating System :: Microsoft :: Windows
Classifier: Operating System :: POSIX :: Linux
Classifier: Operating System :: POSIX :: BSD :: FreeBSD
Classifier: Operating System :: POSIX :: BSD :: NetBSD
Classifier: Operating System :: POSIX :: BSD :: OpenBSD
Classifier: Programming Language :: Python :: 3
Classifier: Programming Language :: Python :: 3.10
Classifier: Programming Language :: Python :: 3.11
Classifier: Programming Language :: Python :: 3.12
Classifier: Programming Language :: Python :: 3.13
Classifier: Programming Language :: Python :: 3.14
Classifier: Programming Language :: Python :: Implementation :: CPython
Classifier: Topic :: Security
Classifier: Topic :: Software Development :: Libraries :: Python Modules
Classifier: Topic :: System :: Archiving :: Packaging
Classifier: Topic :: System :: Installation/Setup
Classifier: Topic :: System :: Software Distribution
Classifier: Topic :: Utilities
Classifier: Typing :: Typed
Requires-Dist: backports-strenum>=1.3.0 ; python_full_version < '3.11'
Requires-Dist: boltons>=25.0.0
Requires-Dist: click-extra>=7.2.0
Requires-Dist: cyclonedx-python-lib[validation]>=11.2.0
Requires-Dist: extra-platforms>=7.0.0
Requires-Dist: more-itertools>=10.8.0
Requires-Dist: packageurl-python>=0.16.0
Requires-Dist: spdx-tools>=0.8.2
Requires-Dist: tabulate[widechars]>=0.9
Requires-Dist: tomli>=2.3.0 ; python_full_version < '3.11'
Requires-Dist: tomli-w>=1.1.0
Requires-Dist: xmltodict>=1.0.0
Requires-Dist: click-extra[hjson] ; extra == 'hjson'
Requires-Dist: click-extra[json5] ; extra == 'json5'
Requires-Dist: click-extra[jsonc] ; extra == 'jsonc'
Requires-Dist: click-extra[xml] ; extra == 'xml'
Requires-Dist: click-extra[yaml] ; extra == 'yaml'
Requires-Python: >=3.10
Project-URL: Changelog, https://github.com/kdeldycke/meta-package-manager/blob/main/changelog.md
Project-URL: Download, https://github.com/kdeldycke/meta-package-manager/releases/tag/v6.1.0
Project-URL: Funding, https://github.com/sponsors/kdeldycke
Project-URL: Homepage, https://github.com/kdeldycke/meta-package-manager
Project-URL: Issues, https://github.com/kdeldycke/meta-package-manager/issues
Project-URL: Repository, https://github.com/kdeldycke/meta-package-manager
Provides-Extra: hjson
Provides-Extra: json5
Provides-Extra: jsonc
Provides-Extra: xml
Provides-Extra: yaml
